lsst_dd_rtd_theme/__init__.py
lsst_dd_rtd_theme/breadcrumbs.html
lsst_dd_rtd_theme/dd_masthead.html
lsst_dd_rtd_theme/footer.html
lsst_dd_rtd_theme/layout.html
lsst_dd_rtd_theme/layout_old.html
lsst_dd_rtd_theme/search.html
lsst_dd_rtd_theme/searchbox.html
lsst_dd_rtd_theme/theme.conf
lsst_dd_rtd_theme/versions.html
lsst_dd_rtd_theme/static/lsst-logo-dark.svg
lsst_dd_rtd_theme/static/css/badge_only.css
lsst_dd_rtd_theme/static/css/badge_only.css.map
lsst_dd_rtd_theme/static/css/theme.css
lsst_dd_rtd_theme/static/css/theme.css.map
lsst_dd_rtd_theme/static/fonts/FontAwesome.otf
lsst_dd_rtd_theme/static/fonts/Inconsolata-Bold.ttf
lsst_dd_rtd_theme/static/fonts/Inconsolata-Regular.ttf
lsst_dd_rtd_theme/static/fonts/Lato-Bold.ttf
lsst_dd_rtd_theme/static/fonts/Lato-Regular.ttf
lsst_dd_rtd_theme/static/fonts/RobotoSlab-Bold.ttf
lsst_dd_rtd_theme/static/fonts/RobotoSlab-Regular.ttf
lsst_dd_rtd_theme/static/fonts/fontawesome-webfont.eot
lsst_dd_rtd_theme/static/fonts/fontawesome-webfont.svg
lsst_dd_rtd_theme/static/fonts/fontawesome-webfont.ttf
lsst_dd_rtd_theme/static/fonts/fontawesome-webfont.woff
lsst_dd_rtd_theme/static/js/modernizr.min.js
lsst_dd_rtd_theme/static/js/theme.js
lsst_dd_rtd_theme-0.2.4.dist-info/LICENSE
lsst_dd_rtd_theme-0.2.4.dist-info/METADATA
lsst_dd_rtd_theme-0.2.4.dist-info/WHEEL
lsst_dd_rtd_theme-0.2.4.dist-info/top_level.txt
lsst_dd_rtd_theme-0.2.4.dist-info/RECORD
