Metadata-Version: 2.1
Name: lsst-dd-rtd-theme
Version: 0.2.4
Summary: LSST Data Management technical note Sphinx theme.
Home-page: https://github.com/lsst-sqre/lsst_dd_rtd_theme
Author: Association of Universities for Research in Astronomy, Inc. (AURA)
Author-email: sqre-admin@lists.lsst.org
License: MIT
Project-URL: Issue tracker, https://github.com/lsst-sqre/lsst_dd_rtd_theme/issues
Keywords: lsst
Platform: UNKNOWN
Classifier: Development Status :: 4 - Beta
Classifier: License :: OSI Approved :: MIT License
Classifier: Programming Language :: Python
Classifier: Programming Language :: Python :: 3
Classifier: Operating System :: OS Independent
Classifier: Intended Audience :: Developers
Classifier: Topic :: Documentation
Classifier: Topic :: Documentation :: Sphinx
Classifier: Framework :: Sphinx :: Theme
Classifier: Environment :: Console
Classifier: Natural Language :: English
Requires-Python: >=3.0
License-File: LICENSE
Requires-Dist: Sphinx (>=1.3)
